controllable/__init__.py
controllable/client.py
controllable/decoder.py
controllable/http_client.py
controllable/models.py
controllable-1a0.dist-info/METADATA
controllable-1a0.dist-info/WHEEL
controllable-1a0.dist-info/top_level.txt
controllable-1a0.dist-info/RECORD
