Metadata-Version: 2.1
Name: controllable
Version: 1a0
Requires-Dist: requests
